{
	"ImportPath": "github.com/launchdarkly/go-client",
	"GoVersion": "go1.4.1",
	"Packages": [
		"./..."
	],
	"Deps": [
		{
			"ImportPath": "github.com/garyburd/redigo/internal",
			"Rev": "535138d7bcd717d6531c701ef5933d98b1866257"
		},
		{
			"ImportPath": "github.com/garyburd/redigo/redis",
			"Rev": "535138d7bcd717d6531c701ef5933d98b1866257"
		},
		{
			"ImportPath": "github.com/gregjones/httpcache",
			"Rev": "e3c27449581612aaef17e1ed7a35a6099fcaae3b"
		},
		{
			"ImportPath": "github.com/launchdarkly/eventsource",
			"Rev": "b948508b604ac2c367c19a2229127c32dad38a65"
		}
	]
}
